setup.cfg
setup.py
chainplot/__init__.py
chainplot.egg-info/PKG-INFO
chainplot.egg-info/SOURCES.txt
chainplot.egg-info/dependency_links.txt
chainplot.egg-info/requires.txt
chainplot.egg-info/top_level.txt
chainplot/core/__init__.py
chainplot/core/layers.py
chainplot/core/mapping.py
chainplot/core/old_plot.py
chainplot/core/plot.py
chainplot/core/style.py
chainplot/utils/__init__.py
chainplot/utils/dict_tools.py
chainplot/utils/string_tools.py