Metadata-Version: 1.1
Name: chainplot
Version: 0.2.1
Summary: A(nother) matplotlib wrapper
Home-page: https://github.com/torvaney/chainplot
Author: Ben Torvaney
Author-email: btorvaney@gmail.com
License: UNKNOWN
Download-URL: https://github.com/torvaney/chainplot/tarball/0.1
Keywords: plot,ggplot
Platform: UNKNOWN
